{
  "0": {
    "9": 121,
    "11": 140,
    "13": 13,
    "8": 67,
    "10": 7,
    "12": 61,
    "15": 64,
    "16": 72,
    "17": 85,
    "18": 69,
    "14": 57,
    "19": 23,
    "7": 7,
    "20": 15,
    "21": 2
  },
  "1": {
    "9": 112,
    "12": 63,
    "13": 11,
    "16": 59,
    "17": 84,
    "11": 120,
    "14": 49,
    "15": 67,
    "18": 58,
    "8": 67,
    "20": 9,
    "19": 21,
    "7": 10,
    "10": 8,
    "22": 2,
    "21": 1
  },
  "2": {
    "9": 108,
    "11": 135,
    "12": 63,
    "14": 57,
    "15": 63,
    "16": 60,
    "8": 65,
    "13": 9,
    "17": 88,
    "18": 50,
    "10": 8,
    "19": 27,
    "21": 10,
    "7": 10,
    "20": 13
  },
  "3": {},
  "4": {
    "15": 10,
    "8": 6,
    "9": 13,
    "11": 17,
    "16": 5,
    "18": 7,
    "19": 1,
    "12": 3,
    "17": 7,
    "14": 2,
    "20": 1
  },
  "5": {
    "8": 68,
    "9": 103,
    "11": 128,
    "13": 15,
    "14": 59,
    "19": 24,
    "21": 7,
    "12": 72,
    "15": 56,
    "16": 58,
    "17": 76,
    "18": 70,
    "7": 6,
    "10": 10,
    "20": 11
  },
  "6": {
    "9": 113,
    "11": 121,
    "12": 75,
    "14": 49,
    "15": 53,
    "16": 76,
    "18": 74,
    "20": 19,
    "8": 67,
    "17": 72,
    "7": 8,
    "19": 24,
    "13": 5,
    "10": 5,
    "21": 1,
    "22": 1
  },
  "7": {
    "8": 69,
    "9": 104,
    "11": 117,
    "12": 77,
    "14": 53,
    "13": 23,
    "17": 82,
    "18": 58,
    "19": 16,
    "20": 7,
    "15": 46,
    "16": 67,
    "7": 7,
    "10": 13,
    "21": 3
  },
  "8": {
    "8": 69,
    "9": 115,
    "11": 128,
    "12": 73,
    "14": 47,
    "16": 78,
    "17": 81,
    "18": 58,
    "13": 11,
    "15": 60,
    "19": 35,
    "20": 6,
    "7": 6,
    "10": 3,
    "21": 6
  },
  "9": {
    "9": 111,
    "10": 16,
    "11": 119,
    "12": 72,
    "13": 12,
    "14": 67,
    "15": 63,
    "16": 73,
    "8": 61,
    "17": 79,
    "18": 74,
    "19": 41,
    "20": 25,
    "7": 10,
    "21": 2
  },
  "10": {
    "8": 8,
    "9": 13,
    "11": 19,
    "12": 4,
    "14": 6,
    "15": 9,
    "16": 14,
    "17": 8,
    "10": 1,
    "13": 4,
    "18": 5,
    "7": 2
  },
  "11": {},
  "12": {
    "8": 69,
    "9": 105,
    "11": 132,
    "12": 65,
    "14": 61,
    "16": 63,
    "17": 84,
    "18": 57,
    "15": 74,
    "10": 7,
    "7": 8,
    "19": 31,
    "20": 16,
    "13": 13,
    "21": 1
  },
  "13": {
    "8": 61,
    "9": 115,
    "11": 128,
    "12": 83,
    "15": 68,
    "16": 72,
    "17": 73,
    "18": 49,
    "14": 47,
    "19": 34,
    "20": 18,
    "13": 11,
    "7": 10,
    "10": 5,
    "21": 3
  },
  "14": {
    "8": 64,
    "9": 114,
    "11": 135,
    "12": 65,
    "14": 43,
    "15": 68,
    "16": 76,
    "17": 78,
    "18": 59,
    "19": 19,
    "13": 15,
    "7": 8,
    "20": 15,
    "21": 6,
    "10": 5
  },
  "15": {
    "8": 66,
    "9": 118,
    "11": 110,
    "12": 98,
    "14": 58,
    "15": 60,
    "16": 83,
    "17": 75,
    "18": 69,
    "19": 27,
    "20": 11,
    "21": 3,
    "10": 6,
    "13": 15,
    "7": 8
  },
  "16": {
    "9": 123,
    "12": 90,
    "14": 56,
    "16": 59,
    "20": 12,
    "21": 4,
    "8": 65,
    "11": 121,
    "17": 69,
    "18": 61,
    "15": 58,
    "13": 9,
    "7": 10,
    "19": 24,
    "10": 3
  },
  "17": {
    "8": 6,
    "9": 10,
    "11": 8,
    "12": 8,
    "13": 1,
    "15": 4,
    "16": 5,
    "17": 11,
    "18": 9,
    "7": 2,
    "19": 1,
    "14": 2,
    "20": 2
  },
  "18": {},
  "19": {
    "9": 111,
    "11": 121,
    "12": 78,
    "15": 52,
    "16": 55,
    "18": 60,
    "8": 65,
    "14": 53,
    "17": 67,
    "13": 10,
    "19": 37,
    "10": 9,
    "7": 8,
    "20": 10,
    "21": 5
  },
  "20": {
    "8": 69,
    "9": 113,
    "11": 129,
    "12": 72,
    "14": 48,
    "15": 64,
    "16": 63,
    "17": 53,
    "10": 6,
    "19": 24,
    "18": 48,
    "7": 8,
    "13": 18,
    "20": 21,
    "21": 3
  },
  "21": {
    "8": 73,
    "9": 118,
    "11": 125,
    "12": 82,
    "14": 54,
    "15": 63,
    "19": 39,
    "18": 62,
    "13": 14,
    "16": 70,
    "17": 59,
    "20": 9,
    "7": 8,
    "10": 6,
    "21": 3
  },
  "22": {
    "9": 108,
    "11": 132,
    "12": 72,
    "15": 60,
    "17": 84,
    "18": 64,
    "19": 24,
    "21": 4,
    "8": 61,
    "14": 47,
    "16": 68,
    "20": 16,
    "7": 8,
    "13": 8,
    "10": 5
  },
  "23": {
    "8": 70,
    "9": 108,
    "11": 131,
    "12": 78,
    "13": 10,
    "16": 63,
    "14": 66,
    "17": 64,
    "15": 67,
    "19": 22,
    "18": 53,
    "7": 9,
    "10": 8,
    "20": 10,
    "21": 6
  },
  "24": {
    "8": 4,
    "9": 5,
    "11": 4,
    "12": 6,
    "16": 4,
    "17": 2,
    "18": 2,
    "13": 1,
    "14": 9,
    "10": 1,
    "15": 1
  },
  "25": {},
  "26": {
    "9": 108,
    "11": 133,
    "14": 73,
    "15": 56,
    "16": 60,
    "17": 61,
    "19": 33,
    "12": 75,
    "13": 16,
    "8": 72,
    "18": 54,
    "10": 10,
    "20": 10,
    "21": 4,
    "7": 7
  },
  "27": {
    "9": 112,
    "11": 121,
    "12": 76,
    "13": 17,
    "15": 78,
    "17": 69,
    "18": 59,
    "19": 29,
    "20": 9,
    "8": 67,
    "16": 55,
    "10": 1,
    "14": 51,
    "7": 11,
    "21": 4
  },
  "28": {
    "8": 64,
    "9": 115,
    "12": 79,
    "14": 55,
    "15": 64,
    "11": 120,
    "13": 17,
    "16": 61,
    "17": 78,
    "18": 49,
    "19": 25,
    "7": 8,
    "20": 10,
    "10": 5,
    "21": 2
  },
  "29": {
    "8": 67,
    "9": 121,
    "11": 136,
    "12": 62,
    "16": 77,
    "17": 65,
    "14": 51,
    "15": 60,
    "18": 59,
    "19": 35,
    "13": 11,
    "20": 20,
    "21": 6,
    "7": 8,
    "10": 7,
    "22": 2
  }
}